{"5/+kWGFK0FqQhGdKe3CkIQ==":"c0539f77-4588-4ac8-83cd-8e56b0997788-640x640.jpg","Fm2w9tdT3zSP+k+Xiw1OXw==":"1502878968889-891x1200.jpg","uGBddwWb09JZpviPurGV/w==":"31361f6305866fe24fc849ffd5b1debe-1662x1080.jpg","NGPd0cJ0WcdzJTllaCI22A==":"31361f6305866fe24fc849ffd5b1debe-1-1662x1080.jpg","TqIZGQ0Q9nnjoti4T1XGZg==":"31361f6305866fe24fc849ffd5b1debe-2-1662x1080.jpg","WChl+xwtbTPtwRuqNI3/Dg==":"0ef62e4df27b4ba7294de889fdbc33e476a08ec9_254x191-254x191.jpg","A8ffHKbO03EoNcZ95O22kA==":"unnamed-170x170.png","QScIBNkvVY3vglHRxWZ8tg==":"tedx-720x731.png","/kbCnPrNp+t8gpUDu2dXIQ==":"skncoe-1200x675.jpg","XjP+JkINAcIBqfTCAYl8kA==":"skncoe-1-1200x675.jpg","geWj6iyYrg2NZhB8QydIIA==":"skncoe-2-1200x675.jpg","5pCdCEj1/hOGAoYJgiOUlQ==":"tedxbern-5-2000x1124.jpg","pUnqHeJDWcrU1rc5zypGEw==":"tedtalks-750x360.jpg","uZiVBfpNiVX4IsUvV6jkhQ==":"tedtalks-1-750x360.jpg","SQByJ7DOHVsclEXhZfei9w==":"31361f6305866fe24fc849ffd5b1debe-3-1662x1080.jpg","qmZd4H4xQItDTL+HnxcBbw==":"31361f6305866fe24fc849ffd5b1debe-4-1662x1080.jpg","Kc+Pvtystu0KNiyR7sBrBA==":"2-8-2000x1998.jpg","tw9uDLYZlE/ZKPPkAkadAA==":"img-20171109-wa0005-1-1080x240.jpg","CGGtf1MuvLFB/KUrA/+mag==":"jumbotron.jpg","IWspY3CiXTj/H+qsqMVbuA==":"ted2-1280x1080.jpg","XAw6S3xfOaSdOANG6g9pwA==":"ted3-1080x720.jpg","3c5FgksmIynQf/DYteoCIA==":"ted4-720x480.jpg","GKABgVKdyqlSfM9RlC5hEg==":"ted4-1-720x480.jpg","U093Ap6CzPlO9lwhk548cg==":"ted5-480x320.jpg","LPCD4gF9m8YG6633Y9MXJA==":"ted5-1-480x320.jpg","+d7goKqsiAqNVAX6OSx03Q==":"ted6-320x213.jpg","qgaaCP91kdHN01q03WvtBw==":"ted6-1-320x213.jpg","VLRsU0u1TtoicViFqKJwtw==":"ted4-1-720x480.jpg","F4j9dHpxwzBk6ZuSWK4EKA==":"ted4-2-720x480.jpg","/8TarGg4y5C+e5BHhyysgA==":"unb-650x403.jpg","BkOe45T9nB/zn35vdDcUVA==":"unb-1-650x403.jpg","cnhVe6kDdnEz2WTRO+dq1w==":"unb-2-650x403.jpg","PKGJPSZX9ELQN1ib8XGG0Q==":"unb-3-650x403.jpg","0NGhCzfSf07KUVbr/pXzww==":"unb-4-650x403.jpg","2/6Y3vfjV11SEXgq6vWUOg==":"rsz_poster-8-1026x684.jpg","zQcAhnJ9TU6CdaGYQ439bA==":"rsz_1rsz_ted4-1-859x572.jpg","DKoKtU8Mg1OFfWIqQT7s2Q==":"rsz_1ted4-1-819x532.jpg","nOfjdSGqsTWTurLNFrGB1w==":"rsz_1ted4-2-819x532.jpg","mGQR9S0IZDvhGbt1zUgR7g==":"rsz_1ted4-3-819x532.jpg","+ZRIYeeJWkRcnzcQc2Z2HA==":"poster%207-2000x1200.jpg","ejdc3cR/5CeehveeDz2c6w==":"poster%207-2000x1200.jpg","Wj6hs+w9OhUa7cDatUoRzw==":"poster%207-2000x1200.jpg","KIC4qyuJTGP52Da6/F4sRA==":"poster%207-2000x1200.jpg","CuyM92edY6v63KB911RoLw==":"poster%207-2000x1200.jpg"}